ghsearcher/__init__.py
ghsearcher/helpers.py
ghsearcher/searcher.py
ghsearcher-0.0.4.dist-info/LICENSE
ghsearcher-0.0.4.dist-info/METADATA
ghsearcher-0.0.4.dist-info/WHEEL
ghsearcher-0.0.4.dist-info/entry_points.txt
ghsearcher-0.0.4.dist-info/top_level.txt
ghsearcher-0.0.4.dist-info/RECORD
