Metadata-Version: 2.1
Name: ghsearcher
Version: 0.0.4
Summary: A tool for searching GitHub
Home-page: https://github.com/dtaivpp/ghsearcher
Author: David Tippett
License: Apache Software License
Keywords: GitHub Replacement Automated Commit
Platform: UNKNOWN
Classifier: Programming Language :: Python :: 3
Classifier: License :: OSI Approved :: Apache Software License
Classifier: Intended Audience :: Developers
Classifier: Operating System :: OS Independent
Requires-Dist: ghapi
Requires-Dist: python-dotenv
Requires-Dist: wheel
